traisms/__init__.py
traisms/sms_template.py
traisms-0.1.0.dist-info/LICENSE
traisms-0.1.0.dist-info/METADATA
traisms-0.1.0.dist-info/WHEEL
traisms-0.1.0.dist-info/top_level.txt
traisms-0.1.0.dist-info/RECORD
