Metadata-Version: 2.1
Name: traisms
Version: 0.1.0
Summary: This package to replace content in the TRAI SMS template
Author: Deepak Pant
Author-email: <deepak.93p@gmail.com>
Keywords: python,trai,sms,replace
Classifier: Programming Language :: Python :: 3
Classifier: Operating System :: OS Independent
Classifier: License :: OSI Approved :: MIT License
Requires-Python: >=3.7
License-File: LICENSE
